{
  "_fv": 57,
  "_type": "tag",
  "definition": {
    "type": "Items",
    "items": [
      {
        "value": "CUSTOM:Yuanshi"
      },
      {
        "value": "CUSTOM:Xixiangyuzhiyuan"
      },
      {
        "value": "CUSTOM:Jijiuchanzhiyuan"
      },
      {
        "value": "CUSTOM:Chuangshijiejing"
      },
      {
        "value": "CUSTOM:Mmola01"
      },
      {
        "value": "CUSTOM:Jinzhimola"
      },
      {
        "value": "CUSTOM:Xiaodaimola"
      },
      {
        "value": "CUSTOM:Ziziyousongshisuixie"
      },
      {
        "value": "CUSTOM:Zuishengsuixie"
      },
      {
        "value": "CUSTOM:Shengzhangbifeisuixie"
      },
      {
        "value": "CUSTOM:Dijingsuixie"
      },
      {
        "value": "CUSTOM:Ranyuansuixie"
      },
      {
        "value": "CUSTOM:Aixubingyusuixie"
      },
      {
        "value": "CUSTOM:Kongyuejinshu"
      },
      {
        "value": "CUSTOM:Xinyuejinshu"
      },
      {
        "value": "CUSTOM:Manyuejinshu"
      },
      {
        "value": "CUSTOM:Ysfc"
      },
      {
        "value": "CUSTOM:Jlza"
      },
      {
        "value": "CUSTOM:Jlliang"
      },
      {
        "value": "CUSTOM:Yhjs"
      },
      {
        "value": "CUSTOM:Zhjs"
      },
      {
        "value": "CUSTOM:Zyjs"
      },
      {
        "value": "CUSTOM:Ryjs"
      },
      {
        "value": "CUSTOM:Lijs"
      },
      {
        "value": "CUSTOM:Zzjll"
      },
      {
        "value": "CUSTOM:Jljsl"
      },
      {
        "value": "CUSTOM:Yhjsl"
      },
      {
        "value": "CUSTOM:Zhjsl"
      },
      {
        "value": "CUSTOM:Zyjsl"
      },
      {
        "value": "CUSTOM:Ryjll"
      },
      {
        "value": "CUSTOM:Lajsl"
      },
      {
        "value": "CUSTOM:Cunqupingzheng"
      }
    ],
    "blocks": [],
    "functions": [],
    "entities": [],
    "biomes": [],
    "damageTypes": [],
    "name": "beacon_payment_items",
    "namespace": "minecraft"
  }
}