{
  "_fv": 69,
  "_type": "item",
  "definition": {
    "renderType": 0,
    "texture": "ysrq_001",
    "customModelName": "Normal",
    "customProperties": {
      "shu": {
        "name": "Yssp_sx"
      }
    },
    "states": [
      {
        "renderType": 0,
        "texture": "ysrq_002",
        "customModelName": "Normal",
        "stateMap": [
          {
            "property": {
              "min": -1.7976931348623157E308,
              "max": 1.7976931348623157E308,
              "name": "CUSTOM:shu",
              "type": "number"
            },
            "value": 2.0
          }
        ]
      },
      {
        "renderType": 0,
        "texture": "ysrq_003",
        "customModelName": "Normal",
        "stateMap": [
          {
            "property": {
              "min": -1.7976931348623157E308,
              "max": 1.7976931348623157E308,
              "name": "CUSTOM:shu",
              "type": "number"
            },
            "value": 3.0
          }
        ]
      },
      {
        "renderType": 0,
        "texture": "ysrq_004",
        "customModelName": "Normal",
        "stateMap": [
          {
            "property": {
              "min": -1.7976931348623157E308,
              "max": 1.7976931348623157E308,
              "name": "CUSTOM:shu",
              "type": "number"
            },
            "value": 4.0
          }
        ]
      }
    ],
    "name": "元素熔珠碎片",
    "rarity": "EPIC",
    "creativeTabs": [
      {
        "value": "CUSTOM:Zhenghuo"
      }
    ],
    "stackSize": 4,
    "enchantability": 0,
    "useDuration": 0,
    "toolType": 1.0,
    "damageCount": 0,
    "recipeRemainder": {
      "value": ""
    },
    "destroyAnyBlock": false,
    "immuneToFire": true,
    "stayInGridWhenCrafting": false,
    "damageOnCrafting": false,
    "enableMeleeDamage": false,
    "damageVsEntity": 0.0,
    "specialInformation": {
      "fixedValue": [
        "§7可用于合成元素熔球"
      ]
    },
    "glowCondition": {
      "fixedValue": false
    },
    "guiBoundTo": "<NONE>",
    "inventorySize": 9,
    "inventoryStackSize": 64,
    "enableRanged": false,
    "shootConstantly": false,
    "rangedItemChargesPower": false,
    "projectile": {
      "value": "Arrow"
    },
    "isFood": false,
    "nutritionalValue": 4,
    "saturation": 0.3,
    "eatResultItem": {
      "value": ""
    },
    "isMeat": false,
    "isAlwaysEdible": false,
    "animation": "none"
  }
}