{
  "_fv": 77,
  "_type": "tool",
  "definition": {
    "toolType": "Axe",
    "renderType": 0,
    "blockingRenderType": 0,
    "texture": "ysf",
    "customModelName": "Normal",
    "blockingModelName": "Normal blocking",
    "name": "§b原石 斧",
    "specialInformation": {
      "fixedValue": []
    },
    "creativeTabs": [
      {
        "value": "CUSTOM:Yuanshigongjuxuanxiangka"
      }
    ],
    "efficiency": 8.5,
    "attackSpeed": 1.0,
    "enchantability": 15,
    "damageVsEntity": 9.5,
    "usageCount": 320,
    "repairItems": [
      {
        "value": "CUSTOM:Yuanshi"
      }
    ],
    "immuneToFire": true,
    "blockDropsTier": "STONE",
    "blocksAffected": [],
    "stayInGridWhenCrafting": false,
    "damageOnCrafting": false
  }
}