{
  "_fv": 57,
  "_type": "tool",
  "definition": {
    "toolType": "Pickaxe",
    "renderType": 0,
    "blockingRenderType": 0,
    "texture": "liezfg",
    "customModelName": "Normal",
    "blockingModelName": "Normal blocking",
    "name": "§9『涤净青金』§a绽放镐",
    "specialInformation": {
      "fixedValue": [
        "§d挖掘方块时：",
        "§7 - 概率在玩家位置生成草原核"
      ]
    },
    "creativeTab": {
      "value": "CUSTOM:Yuanshigongjuxuanxiangka"
    },
    "harvestLevel": 4,
    "efficiency": 8.0,
    "attackSpeed": 1.0,
    "enchantability": 15,
    "damageVsEntity": 7.0,
    "usageCount": 2561,
    "blocksAffected": [],
    "repairItems": [
      {
        "value": "CUSTOM:Shengzhangbifeisuixie"
      },
      {
        "value": "CUSTOM:Dijingsuixie"
      },
      {
        "value": "CUSTOM:Yuanshi"
      }
    ],
    "immuneToFire": true,
    "stayInGridWhenCrafting": false,
    "damageOnCrafting": false,
    "onBlockDestroyedWithTool": {
      "name": "Zfgsx"
    }
  }
}