{
  "_fv": 71,
  "_type": "tool",
  "definition": {
    "toolType": "Pickaxe",
    "renderType": 0,
    "blockingRenderType": 0,
    "texture": "zzg",
    "customModelName": "Normal",
    "blockingModelName": "Normal blocking",
    "name": "§a『自在松石』镐",
    "specialInformation": {
      "fixedValue": [
        "§6[SHIFT+右键]",
        "§7 - 消耗耐久并飞向高空！"
      ]
    },
    "creativeTabs": [
      {
        "value": "CUSTOM:Yuanshigongjuxuanxiangka"
      }
    ],
    "efficiency": 8.5,
    "attackSpeed": 1.2,
    "enchantability": 15,
    "damageVsEntity": 6.0,
    "usageCount": 1561,
    "repairItems": [
      {
        "value": "CUSTOM:Ziziyousongshisuixie"
      },
      {
        "value": "CUSTOM:Yuanshi"
      }
    ],
    "immuneToFire": true,
    "blockDropsTier": "DIAMOND",
    "blocksAffected": [],
    "stayInGridWhenCrafting": false,
    "damageOnCrafting": false,
    "onRightClickedInAir": {
      "name": "Zizaigaoshuxing"
    }
  }
}