{
  "_fv": 69,
  "_type": "recipe",
  "definition": {
    "recipeType": "Smithing",
    "recipeRetstackSize": 1,
    "group": "",
    "cookingBookCategory": "MISC",
    "xpReward": 0.0,
    "cookingTime": 200,
    "craftingBookCategory": "MISC",
    "recipeShapeless": false,
    "smithingInputStack": {
      "value": "Items.IRON_SWORD"
    },
    "smithingInputAdditionStack": {
      "value": "CUSTOM:Sjzst"
    },
    "smithingInputTemplateStack": {
      "value": "CUSTOM:Mmola01"
    },
    "smithingReturnStack": {
      "value": "CUSTOM:Zstj"
    },
    "name": "zsjsj_1",
    "namespace": "mod"
  }
}